logflow/__init__.py
logflow/logger.py
logflowclient-0.2.1.dist-info/licenses/LICENSE
logflowclient-0.2.1.dist-info/METADATA
logflowclient-0.2.1.dist-info/WHEEL
logflowclient-0.2.1.dist-info/top_level.txt
logflowclient-0.2.1.dist-info/RECORD
